{
  "parent": "minecraft:recipes/root",
  "criteria": {
    "has_mod_crate_block_corn_layer_1": {
      "conditions": {
        "items": [
          {
            "items": [
              "eyvb:mod_crate_block_corn_layer_1"
            ]
          }
        ]
      },
      "trigger": "minecraft:inventory_changed"
    },
    "has_the_recipe": {
      "conditions": {
        "recipe": "minecraft:mod_crate_block_corn_layer_1_to_corn"
      },
      "trigger": "minecraft:recipe_unlocked"
    }
  },
  "requirements": [
    [
      "has_mod_crate_block_corn_layer_1",
      "has_the_recipe"
    ]
  ],
  "rewards": {
    "recipes": [
      "minecraft:mod_crate_block_corn_layer_1_to_corn"
    ]
  },
  "sends_telemetry_event": false
}